scikit_lib/__init__.py
scikit_lib/scikit_lib.py
scikit_lib-0.1.2.dist-info/licenses/LICENSE
scikit_lib-0.1.2.dist-info/METADATA
scikit_lib-0.1.2.dist-info/WHEEL
scikit_lib-0.1.2.dist-info/top_level.txt
scikit_lib-0.1.2.dist-info/RECORD
